plutils/__init__.py
plutils/log.py
utils_pl-0.1.2.dist-info/METADATA
utils_pl-0.1.2.dist-info/WHEEL
utils_pl-0.1.2.dist-info/top_level.txt
utils_pl-0.1.2.dist-info/RECORD
